pytiming/__init__.py
pytiming-0.0.2.dist-info/LICENSE
pytiming-0.0.2.dist-info/METADATA
pytiming-0.0.2.dist-info/WHEEL
pytiming-0.0.2.dist-info/top_level.txt
pytiming-0.0.2.dist-info/RECORD
